{
  "captured_at": "2026-07-06T12:05:02.146691+00:00",
  "symbols": [
    {
      "symbol": "BTC",
      "pair": "BTC/USD",
      "status": "ok",
      "timeframes": {
        "1H": {
          "status": "ok",
          "last_close": 61902.31,
          "last_time": "2026-07-03T12:00:00Z",
          "ema8": 61736.18566357122,
          "ema20": 61527.1846638553,
          "ema55": 60883.15086695561,
          "rsi14": 63.61019410340112,
          "atr14": 363.28057426959487,
          "adx14": 40.748050544831464,
          "vol20": 0.0378888177,
          "last_vol": 0.06491663,
          "bar_count": 168
        },
        "4H": {
          "status": "ok",
          "last_close": 64260.838,
          "last_time": "2026-06-13T12:00:00Z",
          "ema8": 63731.0001788223,
          "ema20": 63270.56097279712,
          "ema55": null,
          "rsi14": 64.47525817025652,
          "atr14": 815.888778960034,
          "adx14": 24.50219524890815,
          "vol20": 0.2136999173,
          "last_vol": 0.215947966,
          "bar_count": 42
        },
        "1D": {
          "status": "ok",
          "last_close": 61843.115,
          "last_time": "2026-07-06T00:00:00Z",
          "ema8": 61891.53469392027,
          "ema20": 62293.051780962494,
          "ema55": 66111.8480457431,
          "rsi14": 45.48319090852485,
          "atr14": 2178.8912870641066,
          "adx14": 28.63054356986236,
          "vol20": 1.71397616145,
          "last_vol": 0.559864616,
          "bar_count": 200
        }
      }
    },
    {
      "symbol": "ETH",
      "pair": "ETH/USD",
      "status": "ok",
      "timeframes": {
        "1H": {
          "status": "ok",
          "last_close": 1738.385,
          "last_time": "2026-07-06T12:00:00Z",
          "ema8": 1760.5855963267907,
          "ema20": 1768.1762368671402,
          "ema55": 1762.0560612519366,
          "rsi14": 31.62584485417979,
          "atr14": 12.581543020045272,
          "adx14": 21.533221557609828,
          "vol20": 0.49135251770000005,
          "last_vol": 0.574768394,
          "bar_count": 240
        },
        "4H": {
          "status": "ok",
          "last_close": 1797.435,
          "last_time": "2026-06-16T08:00:00Z",
          "ema8": 1776.1445025344756,
          "ema20": 1738.324153992673,
          "ema55": 1683.1927971332375,
          "rsi14": 65.74966498532056,
          "atr14": 31.031317856443284,
          "adx14": 37.30014230735282,
          "vol20": 6.3383038449,
          "last_vol": 3.591442894,
          "bar_count": 59
        },
        "1D": {
          "status": "ok",
          "last_close": 1738.385,
          "last_time": "2026-07-06T00:00:00Z",
          "ema8": 1712.4511943419473,
          "ema20": 1697.5865358890408,
          "ema55": 1822.0754632895412,
          "rsi14": 52.352303235085586,
          "atr14": 78.55056566237563,
          "adx14": 23.936885962012003,
          "vol20": 29.046859750150002,
          "last_vol": 4.805074912,
          "bar_count": 200
        }
      }
    },
    {
      "symbol": "SOL",
      "pair": "SOL/USD",
      "status": "ok",
      "timeframes": {
        "1H": {
          "status": "ok",
          "last_close": 80.6,
          "last_time": "2026-07-05T07:00:00Z",
          "ema8": 80.73350318266242,
          "ema20": 81.20564060389546,
          "ema55": 81.07819141160269,
          "rsi14": 37.50904885270488,
          "atr14": 0.6164098326409224,
          "adx14": 26.262394817460613,
          "vol20": 10.369196022299999,
          "last_vol": 1.676608,
          "bar_count": 211
        },
        "4H": {
          "status": "ok",
          "last_close": 71.18585,
          "last_time": "2026-06-15T00:00:00Z",
          "ema8": 69.18459524974006,
          "ema20": 68.03347326357357,
          "ema55": null,
          "rsi14": 70.94298695796763,
          "atr14": 1.438465677602492,
          "adx14": 32.14399600442278,
          "vol20": 38.17951529705,
          "last_vol": 41.96774286,
          "bar_count": 51
        },
        "1D": {
          "status": "ok",
          "last_close": 79.3662224135,
          "last_time": "2026-07-06T00:00:00Z",
          "ema8": 78.70797141379343,
          "ema20": 75.67277073349146,
          "ema55": 76.71026415854585,
          "rsi14": 58.48917190637526,
          "atr14": 4.279012237627972,
          "adx14": 20.246914600509513,
          "vol20": 387.315378351,
          "last_vol": 90.496539873,
          "bar_count": 200
        }
      }
    },
    {
      "symbol": "XRP",
      "pair": "XRP/USD",
      "status": "ok",
      "timeframes": {
        "1H": {
          "status": "ok",
          "last_close": 1.124335,
          "last_time": "2026-07-06T12:00:00Z",
          "ema8": 1.1364366499278264,
          "ema20": 1.1399483456785757,
          "ema55": 1.1370670217469883,
          "rsi14": 36.843642904458235,
          "atr14": 0.009255590514062186,
          "adx14": 14.022541719347888,
          "vol20": 259.9053861562,
          "last_vol": 0,
          "bar_count": 240
        },
        "4H": {
          "status": "ok",
          "last_close": 1.2745,
          "last_time": "2026-06-15T16:00:00Z",
          "ema8": 1.215354609225215,
          "ema20": 1.178744154282048,
          "ema55": 1.1447194051545455,
          "rsi14": 79.70948555997208,
          "atr14": 0.02392907654810577,
          "adx14": 36.00890853265487,
          "vol20": 2159.88536099295,
          "last_vol": 5516.075778784,
          "bar_count": 55
        },
        "1D": {
          "status": "ok",
          "last_close": 1.124335,
          "last_time": "2026-07-06T00:00:00Z",
          "ema8": 1.114148343219967,
          "ema20": 1.115664287091053,
          "ema55": 1.1927796965679593,
          "rsi14": 49.0886150431934,
          "atr14": 0.04991426445765914,
          "adx14": 22.1223221494175,
          "vol20": 16320.87520602495,
          "last_vol": 3205.787895585,
          "bar_count": 200
        }
      }
    },
    {
      "symbol": "DOGE",
      "pair": "DOGE/USD",
      "status": "ok",
      "timeframes": {
        "1H": {
          "status": "ok",
          "last_close": 0.07550115,
          "last_time": "2026-07-06T12:00:00Z",
          "ema8": 0.07659770688394138,
          "ema20": 0.07688297113211101,
          "ema55": 0.07677484490297551,
          "rsi14": 34.964085160431125,
          "atr14": 0.0006412471857636553,
          "adx14": 15.841285128837853,
          "vol20": 3870.9820827188,
          "last_vol": 18763.354408417,
          "bar_count": 240
        },
        "4H": {
          "status": "ok",
          "last_close": 0.0889035,
          "last_time": "2026-06-15T16:00:00Z",
          "ema8": 0.08881943296486053,
          "ema20": 0.08785038772668134,
          "ema55": 0.08596392636363635,
          "rsi14": 57.76603942970511,
          "atr14": 0.0016380725620431503,
          "adx14": 30.59865226682738,
          "vol20": 11571.215871772301,
          "last_vol": 51621.913183825,
          "bar_count": 55
        },
        "1D": {
          "status": "ok",
          "last_close": 0.07550115,
          "last_time": "2026-07-06T00:00:00Z",
          "ema8": 0.07599875031347007,
          "ema20": 0.07824458457032717,
          "ema55": 0.08623189818631924,
          "rsi14": 37.507120530991855,
          "atr14": 0.0037698164527897584,
          "adx14": 34.222470027212076,
          "vol20": 65075.401714048254,
          "last_vol": 51927.707090634,
          "bar_count": 200
        }
      }
    },
    {
      "symbol": "AVAX",
      "pair": "AVAX/USD",
      "status": "ok",
      "timeframes": {
        "1H": {
          "status": "ok",
          "last_close": 6.9037,
          "last_time": "2026-07-06T00:00:00Z",
          "ema8": 6.9162017000966625,
          "ema20": 6.90283009487994,
          "ema55": 6.881922561225726,
          "rsi14": 50.783091714375786,
          "atr14": 0.05792071051288043,
          "adx14": 18.204146963771283,
          "vol20": 33.70254947735,
          "last_vol": 75.718408932,
          "bar_count": 228
        },
        "4H": {
          "status": "ok",
          "last_close": 7.028025,
          "last_time": "2026-06-15T12:00:00Z",
          "ema8": 6.798080633496434,
          "ema20": 6.712119489696202,
          "ema55": null,
          "rsi14": 66.2164243272408,
          "atr14": 0.14523805521292757,
          "adx14": 20.45904989210775,
          "vol20": 71.5954811634,
          "last_vol": 154.753148913,
          "bar_count": 54
        },
        "1D": {
          "status": "ok",
          "last_close": 6.71503,
          "last_time": "2026-07-06T00:00:00Z",
          "ema8": 6.759943644409922,
          "ema20": 6.735483471150359,
          "ema55": 7.4094734138709235,
          "rsi14": 47.032897359017774,
          "atr14": 0.3879938708142547,
          "adx14": 25.49053885582716,
          "vol20": 1271.1960145876499,
          "last_vol": 628.389503881,
          "bar_count": 200
        }
      }
    },
    {
      "symbol": "LINK",
      "pair": "LINK/USD",
      "status": "ok",
      "timeframes": {
        "1H": {
          "status": "ok",
          "last_close": 7.816065,
          "last_time": "2026-07-06T12:00:00Z",
          "ema8": 7.915046236060858,
          "ema20": 7.949233702806284,
          "ema55": 7.933286732194878,
          "rsi14": 35.04952197298999,
          "atr14": 0.06078024146855624,
          "adx14": 18.572819117620103,
          "vol20": 32.931844562100004,
          "last_vol": 88.788182351,
          "bar_count": 240
        },
        "4H": {
          "status": "ok",
          "last_close": 8.401725,
          "last_time": "2026-06-15T16:00:00Z",
          "ema8": 8.247875694165208,
          "ema20": 8.08148551505062,
          "ema55": 7.875662545454546,
          "rsi14": 66.16209285028484,
          "atr14": 0.1600207874168332,
          "adx14": 28.722770202419717,
          "vol20": 221.38637899695,
          "last_vol": 20.40269366,
          "bar_count": 55
        },
        "1D": {
          "status": "ok",
          "last_close": 7.816065,
          "last_time": "2026-07-06T00:00:00Z",
          "ema8": 7.767833279114352,
          "ema20": 7.759068105696197,
          "ema55": 8.229462899833125,
          "rsi14": 49.29064020464621,
          "atr14": 0.4161421740548528,
          "adx14": 20.281741234699563,
          "vol20": 542.420252198,
          "last_vol": 483.909209393,
          "bar_count": 200
        }
      }
    },
    {
      "symbol": "DOT",
      "pair": "DOT/USD",
      "status": "ok",
      "timeframes": {
        "1H": {
          "status": "ok",
          "last_close": 0.84865,
          "last_time": "2026-07-06T12:00:00Z",
          "ema8": 0.862480933954615,
          "ema20": 0.8685454473780511,
          "ema55": 0.8709817332043843,
          "rsi14": 28.43228328983831,
          "atr14": 0.007231854991422954,
          "adx14": 18.052213061681552,
          "vol20": 34.7164858696,
          "last_vol": 4.684917622,
          "bar_count": 240
        },
        "4H": {
          "status": "ok",
          "last_close": 0.996965,
          "last_time": "2026-06-14T20:00:00Z",
          "ema8": 0.972408801964979,
          "ema20": 0.9678466732016163,
          "ema55": null,
          "rsi14": 60.764455085435785,
          "atr14": 0.020054031708428448,
          "adx14": 17.299586855787442,
          "vol20": 267.42045439555,
          "last_vol": 1248.226616739,
          "bar_count": 50
        },
        "1D": {
          "status": "ok",
          "last_close": 0.84865,
          "last_time": "2026-07-06T00:00:00Z",
          "ema8": 0.8602317069418486,
          "ema20": 0.8899152850378048,
          "ema55": 1.0122093749030094,
          "rsi14": 36.311987571330874,
          "atr14": 0.049351987270082776,
          "adx14": 36.858841954777596,
          "vol20": 1772.2613032165998,
          "last_vol": 346.555903389,
          "bar_count": 200
        }
      }
    },
    {
      "symbol": "LTC",
      "pair": "LTC/USD",
      "status": "ok",
      "timeframes": {
        "1H": {
          "status": "ok",
          "last_close": 44.08535,
          "last_time": "2026-07-06T12:00:00Z",
          "ema8": 44.61481389024996,
          "ema20": 44.88968061934805,
          "ema55": 44.75344503241433,
          "rsi14": 33.89082820801802,
          "atr14": 0.40103271693529763,
          "adx14": 22.067286568647074,
          "vol20": 4.9333019838,
          "last_vol": 10.316431615,
          "bar_count": 240
        },
        "4H": {
          "status": "ok",
          "last_close": 45.827,
          "last_time": "2026-06-16T00:00:00Z",
          "ema8": 45.45947245426256,
          "ema20": 44.693506163133385,
          "ema55": 43.293619033800674,
          "rsi14": 68.50606184849738,
          "atr14": 0.6880553385702182,
          "adx14": 46.48900292822292,
          "vol20": 5.04620025445,
          "last_vol": 0.733623785,
          "bar_count": 57
        },
        "1D": {
          "status": "ok",
          "last_close": 44.08535,
          "last_time": "2026-07-06T00:00:00Z",
          "ema8": 44.045900474618364,
          "ema20": 43.90738347301291,
          "ema55": 46.73213106515237,
          "rsi14": 48.81307557352175,
          "atr14": 2.248893049283874,
          "adx14": 16.948375571483712,
          "vol20": 59.18185012585,
          "last_vol": 42.500025196,
          "bar_count": 200
        }
      }
    },
    {
      "symbol": "UNI",
      "pair": "UNI/USD",
      "status": "ok",
      "timeframes": {
        "1H": {
          "status": "ok",
          "last_close": 3.15175,
          "last_time": "2026-07-05T16:00:00Z",
          "ema8": 3.148671756598998,
          "ema20": 3.1674472623218937,
          "ema55": 3.1685707779018206,
          "rsi14": 42.10974190797064,
          "atr14": 0.0253768807262274,
          "adx14": 23.697765347593112,
          "vol20": 79.1223166377,
          "last_vol": 0,
          "bar_count": 220
        },
        "4H": {
          "status": "ok",
          "last_close": 2.68615,
          "last_time": "2026-06-15T08:00:00Z",
          "ema8": 2.5832273793107405,
          "ema20": 2.5499189717399338,
          "ema55": null,
          "rsi14": 68.53076600320102,
          "atr14": 0.12320489929471493,
          "adx14": 78.14436816551049,
          "vol20": 498.3830392189,
          "last_vol": 1477.74024041,
          "bar_count": 53
        },
        "1D": {
          "status": "ok",
          "last_close": 3.066985,
          "last_time": "2026-07-06T00:00:00Z",
          "ema8": 3.0720339000342536,
          "ema20": 2.9987678233163075,
          "ema55": 3.047673827254798,
          "rsi14": 53.82200573064915,
          "atr14": 0.2624427754815661,
          "adx14": 35.025189141346104,
          "vol20": 3243.1328557418,
          "last_vol": 152.101646133,
          "bar_count": 200
        }
      }
    }
  ]
}