{
  "captured_at": "2026-06-29T00:05:03.850955+00:00",
  "symbols": [
    {
      "symbol": "BTC",
      "pair": "BTC/USD",
      "status": "ok",
      "timeframes": {
        "1H": {
          "status": "ok",
          "last_close": 59332.7,
          "last_time": "2026-06-26T01:00:00Z",
          "ema8": 59598.95387967267,
          "ema20": 59963.75413903341,
          "ema55": 60924.0680550374,
          "rsi14": 40.647525968851504,
          "atr14": 642.7094384611775,
          "adx14": 25.790113779832392,
          "vol20": 0.14648558395,
          "last_vol": 0.022056336,
          "bar_count": 169
        },
        "4H": {
          "status": "ok",
          "last_close": 60967.3405,
          "last_time": "2026-06-06T04:00:00Z",
          "ema8": 61462.172923262755,
          "ema20": 63546.589885567984,
          "ema55": null,
          "rsi14": 28.79735087854796,
          "atr14": 1626.6838666977726,
          "adx14": 71.93639800687522,
          "vol20": 1.2040861647,
          "last_vol": 0.942504671,
          "bar_count": 43
        },
        "1D": {
          "status": "ok",
          "last_close": 59312.369,
          "last_time": "2026-06-29T00:00:00Z",
          "ema8": 60600.61913351258,
          "ema20": 62685.90179596102,
          "ema55": 67355.4941001386,
          "rsi14": 30.280433893252408,
          "atr14": 2148.409256949128,
          "adx14": 35.52129077771065,
          "vol20": 1.52104153415,
          "last_vol": 0.000537,
          "bar_count": 200
        }
      }
    },
    {
      "symbol": "ETH",
      "pair": "ETH/USD",
      "status": "ok",
      "timeframes": {
        "1H": {
          "status": "ok",
          "last_close": 1564.8945,
          "last_time": "2026-06-29T00:00:00Z",
          "ema8": 1566.1791355297912,
          "ema20": 1570.1623648695172,
          "ema55": 1576.4326404828196,
          "rsi14": 45.23014662835139,
          "atr14": 12.26560357492946,
          "adx14": 24.789707378971805,
          "vol20": 1.2497573627,
          "last_vol": 0,
          "bar_count": 240
        },
        "4H": {
          "status": "ok",
          "last_close": 1672.051,
          "last_time": "2026-06-08T04:00:00Z",
          "ema8": 1645.4192661842026,
          "ema20": 1654.5099819342943,
          "ema55": 1813.1081636363635,
          "rsi14": 48.82473114781336,
          "atr14": 50.00599757055005,
          "adx14": 53.35513002619766,
          "vol20": 14.01823511785,
          "last_vol": 13.635272265,
          "bar_count": 55
        },
        "1D": {
          "status": "ok",
          "last_close": 1564.8945,
          "last_time": "2026-06-29T00:00:00Z",
          "ema8": 1603.6493217503967,
          "ema20": 1672.916617922197,
          "ema55": 1852.4008757664183,
          "rsi14": 31.124990257964612,
          "atr14": 74.72807946374435,
          "adx14": 30.467736762515067,
          "vol20": 31.3184967148,
          "last_vol": 0,
          "bar_count": 200
        }
      }
    },
    {
      "symbol": "SOL",
      "pair": "SOL/USD",
      "status": "ok",
      "timeframes": {
        "1H": {
          "status": "ok",
          "last_close": 72.619442045,
          "last_time": "2026-06-27T16:00:00Z",
          "ema8": 72.32607858887411,
          "ema20": 71.8968624819227,
          "ema55": 70.68076390295082,
          "rsi14": 62.66273459282912,
          "atr14": 0.7696354460276073,
          "adx14": 38.28301462047916,
          "vol20": 10.9974507618,
          "last_vol": 4.613002697,
          "bar_count": 208
        },
        "4H": {
          "status": "ok",
          "last_close": 64.93865,
          "last_time": "2026-06-07T12:00:00Z",
          "ema8": 64.10849834160588,
          "ema20": 65.74343359187098,
          "ema55": null,
          "rsi14": 38.179126383962725,
          "atr14": 2.157753024602143,
          "adx14": 59.105207135584386,
          "vol20": 106.62719450535,
          "last_vol": 86.400484577,
          "bar_count": 51
        },
        "1D": {
          "status": "ok",
          "last_close": 71.0905,
          "last_time": "2026-06-29T00:00:00Z",
          "ema8": 70.60774451113956,
          "ema20": 71.05369787192382,
          "ema55": 75.69141171078672,
          "rsi14": 48.09940807532837,
          "atr14": 4.063866291523712,
          "adx14": 15.847497950262838,
          "vol20": 404.06032723165,
          "last_vol": 0,
          "bar_count": 200
        }
      }
    },
    {
      "symbol": "XRP",
      "pair": "XRP/USD",
      "status": "ok",
      "timeframes": {
        "1H": {
          "status": "ok",
          "last_close": 1.043985,
          "last_time": "2026-06-29T00:00:00Z",
          "ema8": 1.043789072210779,
          "ema20": 1.046109696765786,
          "ema55": 1.049756253941686,
          "rsi14": 46.56842965377087,
          "atr14": 0.008263290333125875,
          "adx14": 14.580564131289748,
          "vol20": 229.59516970195,
          "last_vol": 0,
          "bar_count": 240
        },
        "4H": {
          "status": "ok",
          "last_close": 1.12406,
          "last_time": "2026-06-07T16:00:00Z",
          "ema8": 1.1208801974702218,
          "ema20": 1.1322646261287042,
          "ema55": null,
          "rsi14": 42.449527165901706,
          "atr14": 0.03216166925433995,
          "adx14": 62.282564354412685,
          "vol20": 3782.1825281644,
          "last_vol": 2108.215723036,
          "bar_count": 52
        },
        "1D": {
          "status": "ok",
          "last_close": 1.043985,
          "last_time": "2026-06-29T00:00:00Z",
          "ema8": 1.0679279987447408,
          "ema20": 1.1159092929421652,
          "ema55": 1.2160600875900796,
          "rsi14": 31.703195775162726,
          "atr14": 0.0472005006996867,
          "adx14": 28.017698928858618,
          "vol20": 17251.371919924448,
          "last_vol": 0,
          "bar_count": 200
        }
      }
    },
    {
      "symbol": "DOGE",
      "pair": "DOGE/USD",
      "status": "ok",
      "timeframes": {
        "1H": {
          "status": "ok",
          "last_close": 0.0728955,
          "last_time": "2026-06-29T00:00:00Z",
          "ema8": 0.07294123136640566,
          "ema20": 0.0733300650844347,
          "ema55": 0.0741555438920586,
          "rsi14": 41.05583150410749,
          "atr14": 0.0006161128866833062,
          "adx14": 36.039087796413675,
          "vol20": 159.8118849207,
          "last_vol": 0,
          "bar_count": 240
        },
        "4H": {
          "status": "ok",
          "last_close": 0.083326,
          "last_time": "2026-06-07T16:00:00Z",
          "ema8": 0.08351049186909656,
          "ema20": 0.08475065726411196,
          "ema55": null,
          "rsi14": 38.768174309206884,
          "atr14": 0.002387764417571339,
          "adx14": 60.695621092047354,
          "vol20": 9518.9118175798,
          "last_vol": 734.247702181,
          "bar_count": 52
        },
        "1D": {
          "status": "ok",
          "last_close": 0.0728955,
          "last_time": "2026-06-29T00:00:00Z",
          "ema8": 0.07597702869466415,
          "ema20": 0.08090345817482854,
          "ema55": 0.089343467564953,
          "rsi14": 22.659484983259148,
          "atr14": 0.003822160473325945,
          "adx14": 35.90008833227149,
          "vol20": 54250.067948769196,
          "last_vol": 0,
          "bar_count": 200
        }
      }
    },
    {
      "symbol": "AVAX",
      "pair": "AVAX/USD",
      "status": "ok",
      "timeframes": {
        "1H": {
          "status": "ok",
          "last_close": 6.546355,
          "last_time": "2026-06-27T04:00:00Z",
          "ema8": 6.526255116635026,
          "ema20": 6.425092244279539,
          "ema55": 6.335363866666078,
          "rsi14": 58.78560846517981,
          "atr14": 0.13077462044500693,
          "adx14": 26.752579559057263,
          "vol20": 18.973251716750003,
          "last_vol": 1.604098367,
          "bar_count": 196
        },
        "4H": {
          "status": "ok",
          "last_close": 6.7081,
          "last_time": "2026-06-07T12:00:00Z",
          "ema8": 6.747215878176917,
          "ema20": 7.035563924662323,
          "ema55": null,
          "rsi14": 29.055292560736902,
          "atr14": 0.2609008819830824,
          "adx14": 62.59390209417818,
          "vol20": 109.68674493875001,
          "last_vol": 66.844311301,
          "bar_count": 51
        },
        "1D": {
          "status": "ok",
          "last_close": 6.438665,
          "last_time": "2026-06-29T00:00:00Z",
          "ema8": 6.424558405007671,
          "ema20": 6.643298010604116,
          "ema55": 7.57685664226069,
          "rsi14": 41.20117319971208,
          "atr14": 0.4307111691020353,
          "adx14": 40.17157991101364,
          "vol20": 1002.65451075365,
          "last_vol": 0,
          "bar_count": 200
        }
      }
    },
    {
      "symbol": "LINK",
      "pair": "LINK/USD",
      "status": "ok",
      "timeframes": {
        "1H": {
          "status": "ok",
          "last_close": 7.238095,
          "last_time": "2026-06-29T00:00:00Z",
          "ema8": 7.232472347068521,
          "ema20": 7.253208471687831,
          "ema55": 7.290946403564187,
          "rsi14": 46.5632842407908,
          "atr14": 0.06138751098536092,
          "adx14": 24.029162089621412,
          "vol20": 25.94439654345,
          "last_vol": 248.327,
          "bar_count": 240
        },
        "4H": {
          "status": "ok",
          "last_close": 7.7588,
          "last_time": "2026-06-07T08:00:00Z",
          "ema8": 7.558727967140353,
          "ema20": 7.688475373049776,
          "ema55": null,
          "rsi14": 48.00183541194637,
          "atr14": 0.2392505570816041,
          "adx14": 62.33140771257308,
          "vol20": 384.9879069809,
          "last_vol": 91.765746702,
          "bar_count": 50
        },
        "1D": {
          "status": "ok",
          "last_close": 7.238095,
          "last_time": "2026-06-29T00:00:00Z",
          "ema8": 7.411803949086199,
          "ema20": 7.725357396603173,
          "ema55": 8.361518043907571,
          "rsi14": 32.02141305742251,
          "atr14": 0.359068479612758,
          "adx14": 25.99046416308415,
          "vol20": 796.83681256585,
          "last_vol": 248.327,
          "bar_count": 200
        }
      }
    },
    {
      "symbol": "DOT",
      "pair": "DOT/USD",
      "status": "ok",
      "timeframes": {
        "1H": {
          "status": "ok",
          "last_close": 0.8069185,
          "last_time": "2026-06-28T19:00:00Z",
          "ema8": 0.8078381557500823,
          "ema20": 0.8120696511480966,
          "ema55": 0.8270207081807386,
          "rsi14": 40.422289922281855,
          "atr14": 0.007852756415012107,
          "adx14": 32.31833823203852,
          "vol20": 30.870146145699998,
          "last_vol": 0,
          "bar_count": 235
        },
        "4H": {
          "status": "ok",
          "last_close": 0.9428,
          "last_time": "2026-06-06T20:00:00Z",
          "ema8": 0.9488627977684947,
          "ema20": 0.992392419448279,
          "ema55": null,
          "rsi14": 30.983523741015304,
          "atr14": 0.03830713869329489,
          "adx14": 49.3349593424541,
          "vol20": 833.9235655332001,
          "last_vol": 133.246914,
          "bar_count": 47
        },
        "1D": {
          "status": "ok",
          "last_close": 0.81115,
          "last_time": "2026-06-29T00:00:00Z",
          "ema8": 0.8538623443207534,
          "ema20": 0.9214116094599378,
          "ema55": 1.0566993806740863,
          "rsi14": 23.14989115389021,
          "atr14": 0.05445376242997045,
          "adx14": 45.1918912795678,
          "vol20": 2226.7786285611,
          "last_vol": 12.370052597,
          "bar_count": 200
        }
      }
    },
    {
      "symbol": "LTC",
      "pair": "LTC/USD",
      "status": "ok",
      "timeframes": {
        "1H": {
          "status": "ok",
          "last_close": 42.453,
          "last_time": "2026-06-29T00:00:00Z",
          "ema8": 42.44850899024187,
          "ema20": 42.53075098828981,
          "ema55": 42.35311751571015,
          "rsi14": 48.52784798148258,
          "atr14": 0.42887969877924326,
          "adx14": 23.401160306923526,
          "vol20": 0.72930701085,
          "last_vol": 0,
          "bar_count": 240
        },
        "4H": {
          "status": "ok",
          "last_close": 43.1312,
          "last_time": "2026-06-08T08:00:00Z",
          "ema8": 42.547259914535246,
          "ema20": 43.127663843190575,
          "ema55": 46.89354305194805,
          "rsi14": 45.08854110089799,
          "atr14": 1.2619264339961302,
          "adx14": 62.43091476570136,
          "vol20": 10.0939001648,
          "last_vol": 3.715085874,
          "bar_count": 56
        },
        "1D": {
          "status": "ok",
          "last_close": 42.453,
          "last_time": "2026-06-29T00:00:00Z",
          "ema8": 42.462169076223695,
          "ema20": 43.632645557305466,
          "ema55": 47.491245249075995,
          "rsi14": 38.61745904870034,
          "atr14": 2.297222472084438,
          "adx14": 21.895947124008945,
          "vol20": 31.735898723200002,
          "last_vol": 0,
          "bar_count": 200
        }
      }
    },
    {
      "symbol": "UNI",
      "pair": "UNI/USD",
      "status": "ok",
      "timeframes": {
        "1H": {
          "status": "ok",
          "last_close": 2.940645,
          "last_time": "2026-06-27T07:00:00Z",
          "ema8": 2.945038820785382,
          "ema20": 2.9372050667316403,
          "ema55": 2.9166335304363415,
          "rsi14": 52.234645421232436,
          "atr14": 0.04757714035105366,
          "adx14": 13.422593138130066,
          "vol20": 18.13211392525,
          "last_vol": 4.386036,
          "bar_count": 199
        },
        "4H": {
          "status": "ok",
          "last_close": 2.51013,
          "last_time": "2026-06-07T12:00:00Z",
          "ema8": 2.507353521278869,
          "ema20": 2.5498806541933146,
          "ema55": null,
          "rsi14": 41.908750571506225,
          "atr14": 0.08343331565633494,
          "adx14": 43.78160771205628,
          "vol20": 175.29857543650002,
          "last_vol": 47.543904807,
          "bar_count": 51
        },
        "1D": {
          "status": "ok",
          "last_close": 2.907705,
          "last_time": "2026-06-29T00:00:00Z",
          "ema8": 2.929432396957266,
          "ema20": 2.9192134267962713,
          "ema55": 3.0418995579297934,
          "rsi14": 48.589807574517074,
          "atr14": 0.27842545523767226,
          "adx14": 32.82873586598043,
          "vol20": 4252.68764278595,
          "last_vol": 0,
          "bar_count": 200
        }
      }
    }
  ]
}