{
  "captured_at": "2026-06-29T08:05:03.007336+00:00",
  "symbols": [
    {
      "symbol": "BTC",
      "pair": "BTC/USD",
      "status": "ok",
      "timeframes": {
        "1H": {
          "status": "ok",
          "last_close": 59639.75,
          "last_time": "2026-06-26T09:00:00Z",
          "ema8": 59891.975370879256,
          "ema20": 59918.85178028443,
          "ema55": 60652.235665875494,
          "rsi14": 46.07157189492308,
          "atr14": 671.0916617924423,
          "adx14": 21.443787436736265,
          "vol20": 0.12455593115,
          "last_vol": 0.010739298,
          "bar_count": 169
        },
        "4H": {
          "status": "ok",
          "last_close": 60741.083,
          "last_time": "2026-06-06T12:00:00Z",
          "ema8": 61183.91247129279,
          "ema20": 63077.51633829659,
          "ema55": null,
          "rsi14": 27.61691108052817,
          "atr14": 1565.8003930664095,
          "adx14": 74.96106731846389,
          "vol20": 1.1763861232,
          "last_vol": 0.118508484,
          "bar_count": 43
        },
        "1D": {
          "status": "ok",
          "last_close": 59993.8245,
          "last_time": "2026-06-29T00:00:00Z",
          "ema8": 60752.05368906814,
          "ema20": 62750.80231977055,
          "ema55": 67379.83179656717,
          "rsi14": 33.489481268323956,
          "atr14": 2236.7697926634137,
          "adx14": 35.524800985473696,
          "vol20": 1.5332844968,
          "last_vol": 0.245396253,
          "bar_count": 200
        }
      }
    },
    {
      "symbol": "ETH",
      "pair": "ETH/USD",
      "status": "ok",
      "timeframes": {
        "1H": {
          "status": "ok",
          "last_close": 1578.8855,
          "last_time": "2026-06-29T08:00:00Z",
          "ema8": 1576.5748544026962,
          "ema20": 1574.3609190090028,
          "ema55": 1576.726221073386,
          "rsi14": 53.60820629891934,
          "atr14": 12.80343735507444,
          "adx14": 32.6134663076186,
          "vol20": 1.06861631935,
          "last_vol": 0.06329509,
          "bar_count": 240
        },
        "4H": {
          "status": "ok",
          "last_close": 1672.051,
          "last_time": "2026-06-08T04:00:00Z",
          "ema8": 1645.4193254543236,
          "ema20": 1654.7481478181423,
          "ema55": null,
          "rsi14": 48.67498168236414,
          "atr14": 50.080764392160745,
          "adx14": 55.20024146056314,
          "vol20": 14.01823511785,
          "last_vol": 13.635272265,
          "bar_count": 53
        },
        "1D": {
          "status": "ok",
          "last_close": 1578.8855,
          "last_time": "2026-06-29T00:00:00Z",
          "ema8": 1606.7584328615078,
          "ema20": 1674.2490941126732,
          "ema55": 1852.9005543378469,
          "rsi14": 32.96162710751199,
          "atr14": 77.03190089231578,
          "adx14": 30.467736762515067,
          "vol20": 31.8281531326,
          "last_vol": 10.193128356,
          "bar_count": 200
        }
      }
    },
    {
      "symbol": "SOL",
      "pair": "SOL/USD",
      "status": "ok",
      "timeframes": {
        "1H": {
          "status": "ok",
          "last_close": 70.7205,
          "last_time": "2026-06-28T01:00:00Z",
          "ema8": 70.98079730104347,
          "ema20": 71.33285859604612,
          "ema55": 70.7728026435562,
          "rsi14": 43.1316229953651,
          "atr14": 0.7440489969664433,
          "adx14": 23.058048437594238,
          "vol20": 4.19220413305,
          "last_vol": 0.078535722,
          "bar_count": 209
        },
        "4H": {
          "status": "ok",
          "last_close": 63.9065,
          "last_time": "2026-06-07T16:00:00Z",
          "ema8": 64.06361600208346,
          "ema20": 65.58832251809834,
          "ema55": null,
          "rsi14": 34.23580568893759,
          "atr14": 2.151187137625359,
          "adx14": 56.84625360880115,
          "vol20": 104.56995432685001,
          "last_vol": 65.129398245,
          "bar_count": 50
        },
        "1D": {
          "status": "ok",
          "last_close": 72.811,
          "last_time": "2026-06-29T00:00:00Z",
          "ema8": 70.99007784447289,
          "ema20": 71.21755501478096,
          "ema55": 75.75285813935815,
          "rsi14": 51.74208093295832,
          "atr14": 4.247261573666568,
          "adx14": 15.50333295824107,
          "vol20": 414.8879419778,
          "last_vol": 216.552294923,
          "bar_count": 200
        }
      }
    },
    {
      "symbol": "XRP",
      "pair": "XRP/USD",
      "status": "ok",
      "timeframes": {
        "1H": {
          "status": "ok",
          "last_close": 1.04927,
          "last_time": "2026-06-29T08:00:00Z",
          "ema8": 1.0467545179981639,
          "ema20": 1.0464229530106943,
          "ema55": 1.0489224130317594,
          "rsi14": 52.87763332142626,
          "atr14": 0.00936181152427636,
          "adx14": 21.648340331988454,
          "vol20": 282.39076603925,
          "last_vol": 177.644858,
          "bar_count": 240
        },
        "4H": {
          "status": "ok",
          "last_close": 1.155,
          "last_time": "2026-06-07T20:00:00Z",
          "ema8": 1.1284624181822716,
          "ema20": 1.1346764148303539,
          "ema55": null,
          "rsi14": 52.16519126981224,
          "atr14": 0.03330923608599916,
          "adx14": 58.046880333288236,
          "vol20": 3706.90109971935,
          "last_vol": 3613.483544189,
          "bar_count": 51
        },
        "1D": {
          "status": "ok",
          "last_close": 1.04927,
          "last_time": "2026-06-29T00:00:00Z",
          "ema8": 1.0691024431891853,
          "ema20": 1.1164126262754985,
          "ema55": 1.2162488375900795,
          "rsi14": 32.5892940185916,
          "atr14": 0.048724429271115276,
          "adx14": 28.018096575504558,
          "vol20": 17380.848490489552,
          "last_vol": 2589.531411302,
          "bar_count": 200
        }
      }
    },
    {
      "symbol": "DOGE",
      "pair": "DOGE/USD",
      "status": "ok",
      "timeframes": {
        "1H": {
          "status": "ok",
          "last_close": 0.0727615,
          "last_time": "2026-06-29T08:00:00Z",
          "ema8": 0.07285544173207907,
          "ema20": 0.07307559682503761,
          "ema55": 0.0738340022352321,
          "rsi14": 43.793945761457664,
          "atr14": 0.0006734426769832259,
          "adx14": 36.27543758805545,
          "vol20": 523.5969260515501,
          "last_vol": 0,
          "bar_count": 240
        },
        "4H": {
          "status": "ok",
          "last_close": 0.08625425,
          "last_time": "2026-06-07T20:00:00Z",
          "ema8": 0.08412021955561517,
          "ema20": 0.08491237103260513,
          "ema55": null,
          "rsi14": 50.588565633107464,
          "atr14": 0.0025351462949217466,
          "adx14": 57.76090011292356,
          "vol20": 9167.28662791305,
          "last_vol": 6552.792302673,
          "bar_count": 51
        },
        "1D": {
          "status": "ok",
          "last_close": 0.0727615,
          "last_time": "2026-06-29T00:00:00Z",
          "ema8": 0.07594725091688637,
          "ema20": 0.08089069627006663,
          "ema55": 0.08933868185066729,
          "rsi14": 22.51158122988528,
          "atr14": 0.003922967616183088,
          "adx14": 35.950220465669354,
          "vol20": 54628.4552079865,
          "last_vol": 7567.745184346,
          "bar_count": 200
        }
      }
    },
    {
      "symbol": "AVAX",
      "pair": "AVAX/USD",
      "status": "ok",
      "timeframes": {
        "1H": {
          "status": "ok",
          "last_close": 6.604,
          "last_time": "2026-06-27T14:00:00Z",
          "ema8": 6.559917762861689,
          "ema20": 6.509238984300042,
          "ema55": 6.402776206536239,
          "rsi14": 60.23027464063794,
          "atr14": 0.09996193932344892,
          "adx14": 24.036937264206824,
          "vol20": 6.430614069399999,
          "last_vol": 1.456152617,
          "bar_count": 198
        },
        "4H": {
          "status": "ok",
          "last_close": 6.53549,
          "last_time": "2026-06-07T16:00:00Z",
          "ema8": 6.700166436258998,
          "ema20": 6.990091825204365,
          "ema55": null,
          "rsi14": 25.45462799578769,
          "atr14": 0.26000054019036567,
          "adx14": 63.414549767802136,
          "vol20": 107.35101484825,
          "last_vol": 37.554320963,
          "bar_count": 50
        },
        "1D": {
          "status": "ok",
          "last_close": 6.558455,
          "last_time": "2026-06-29T00:00:00Z",
          "ema8": 6.451178405007671,
          "ema20": 6.654706582032688,
          "ema55": 7.581134856546404,
          "rsi14": 43.844461785872376,
          "atr14": 0.4497390262448925,
          "adx14": 39.31678000283826,
          "vol20": 1005.3718012644,
          "last_vol": 54.345810215,
          "bar_count": 200
        }
      }
    },
    {
      "symbol": "LINK",
      "pair": "LINK/USD",
      "status": "ok",
      "timeframes": {
        "1H": {
          "status": "ok",
          "last_close": 7.323675,
          "last_time": "2026-06-29T08:00:00Z",
          "ema8": 7.295909656323924,
          "ema20": 7.280091092851187,
          "ema55": 7.2933668869093635,
          "rsi14": 56.643762041940406,
          "atr14": 0.06261684488960997,
          "adx14": 22.825488324507855,
          "vol20": 16.6200782055,
          "last_vol": 0,
          "bar_count": 240
        },
        "4H": {
          "status": "ok",
          "last_close": 7.7225,
          "last_time": "2026-06-07T12:00:00Z",
          "ema8": 7.595122926535549,
          "ema20": 7.693832933782827,
          "ema55": null,
          "rsi14": 46.59526641178423,
          "atr14": 0.23515632570715225,
          "adx14": 61.934874663835636,
          "vol20": 377.61236507654996,
          "last_vol": 48.113169026,
          "bar_count": 49
        },
        "1D": {
          "status": "ok",
          "last_close": 7.323675,
          "last_time": "2026-06-29T00:00:00Z",
          "ema8": 7.430821726863977,
          "ema20": 7.733507872793649,
          "ema55": 8.364574472479,
          "rsi14": 34.58022814704884,
          "atr14": 0.3703045510413295,
          "adx14": 25.947048787936925,
          "vol20": 799.2372773549,
          "last_vol": 296.336295781,
          "bar_count": 200
        }
      }
    },
    {
      "symbol": "DOT",
      "pair": "DOT/USD",
      "status": "ok",
      "timeframes": {
        "1H": {
          "status": "ok",
          "last_close": 0.82376,
          "last_time": "2026-06-29T03:00:00Z",
          "ema8": 0.8149182870916981,
          "ema20": 0.8130846178252416,
          "ema55": 0.8234821194111877,
          "rsi14": 58.171159107635376,
          "atr14": 0.00952244738532555,
          "adx14": 28.441189954745393,
          "vol20": 31.30818057655,
          "last_vol": 30.19201229,
          "bar_count": 235
        },
        "4H": {
          "status": "ok",
          "last_close": 0.9560185,
          "last_time": "2026-06-07T00:00:00Z",
          "ema8": 0.9504531795330263,
          "ema20": 0.9892085659000717,
          "ema55": null,
          "rsi14": 35.5501604370324,
          "atr14": 0.03751231215859489,
          "adx14": 48.19223912652997,
          "vol20": 822.8399558311,
          "last_vol": 51.519406497,
          "bar_count": 46
        },
        "1D": {
          "status": "ok",
          "last_close": 0.81691,
          "last_time": "2026-06-29T00:00:00Z",
          "ema8": 0.8551423443207534,
          "ema20": 0.9219601808885093,
          "ema55": 1.0569050949598007,
          "rsi14": 24.658779743078,
          "atr14": 0.0556634052871133,
          "adx14": 44.87126821958886,
          "vol20": 2238.1082304756,
          "last_vol": 238.962090887,
          "bar_count": 200
        }
      }
    },
    {
      "symbol": "LTC",
      "pair": "LTC/USD",
      "status": "ok",
      "timeframes": {
        "1H": {
          "status": "ok",
          "last_close": 42.6119,
          "last_time": "2026-06-29T08:00:00Z",
          "ema8": 42.729743772698605,
          "ema20": 42.69943917288507,
          "ema55": 42.4829201562702,
          "rsi14": 48.71560994236893,
          "atr14": 0.4126116283239663,
          "adx14": 19.53250102586535,
          "vol20": 0.6161192197500001,
          "last_vol": 0,
          "bar_count": 240
        },
        "4H": {
          "status": "ok",
          "last_close": 43.1312,
          "last_time": "2026-06-08T08:00:00Z",
          "ema8": 42.54726088734481,
          "ema20": 43.13409585743577,
          "ema55": null,
          "rsi14": 45.013154126033356,
          "atr14": 1.2634035916165984,
          "adx14": 64.34398461627721,
          "vol20": 10.0939001648,
          "last_vol": 3.715085874,
          "bar_count": 54
        },
        "1D": {
          "status": "ok",
          "last_close": 42.6119,
          "last_time": "2026-06-29T00:00:00Z",
          "ema8": 42.49748018733481,
          "ema20": 43.6477788906388,
          "ema55": 47.496920249076,
          "rsi14": 39.616519354065595,
          "atr14": 2.353172472084438,
          "adx14": 21.895947124008945,
          "vol20": 31.821338378950003,
          "last_vol": 1.708793115,
          "bar_count": 200
        }
      }
    },
    {
      "symbol": "UNI",
      "pair": "UNI/USD",
      "status": "ok",
      "timeframes": {
        "1H": {
          "status": "ok",
          "last_close": 2.94308,
          "last_time": "2026-06-27T19:00:00Z",
          "ema8": 2.9669265147345887,
          "ema20": 2.953522398738251,
          "ema55": 2.9304164948096276,
          "rsi14": 49.26580696931343,
          "atr14": 0.04043024196300592,
          "adx14": 16.50090415837577,
          "vol20": 41.10763628405,
          "last_vol": 344.474537752,
          "bar_count": 203
        },
        "4H": {
          "status": "ok",
          "last_close": 2.48835,
          "last_time": "2026-06-07T16:00:00Z",
          "ema8": 2.503130841338729,
          "ema20": 2.544627840226788,
          "ema55": null,
          "rsi14": 39.86646082489814,
          "atr14": 0.08232625525178541,
          "adx14": 40.96834685564687,
          "vol20": 177.39898946455,
          "last_vol": 48.430712561,
          "bar_count": 50
        },
        "1D": {
          "status": "ok",
          "last_close": 2.94137,
          "last_time": "2026-06-29T00:00:00Z",
          "ema8": 2.9369135080683773,
          "ema20": 2.9224196172724617,
          "ema55": 3.043101879358365,
          "rsi14": 50.41361004331619,
          "atr14": 0.28457795523767226,
          "adx14": 32.87774292157882,
          "vol20": 4385.196299552,
          "last_vol": 2650.173135321,
          "bar_count": 200
        }
      }
    }
  ]
}