{
  "captured_at": "2026-07-20T11:05:05.292238+00:00",
  "symbols": [
    {
      "symbol": "BTC",
      "pair": "BTC/USD",
      "status": "ok",
      "timeframes": {
        "1H": {
          "status": "ok",
          "last_close": 64268.288,
          "last_time": "2026-07-20T11:00:00Z",
          "ema8": 64237.28529636915,
          "ema20": 64344.43499514083,
          "ema55": 64336.48226544989,
          "rsi14": 47.373681471531384,
          "atr14": 313.2357815265372,
          "adx14": 21.41082326779395,
          "vol20": 0.02896029315,
          "last_vol": 7.7e-05,
          "bar_count": 240
        },
        "4H": {
          "status": "ok",
          "last_close": 64268.288,
          "last_time": "2026-07-20T08:00:00Z",
          "ema8": 64436.81057652778,
          "ema20": 64321.59184728233,
          "ema55": 63963.602371012756,
          "rsi14": 50.25354969898982,
          "atr14": 569.5011329768923,
          "adx14": 24.176079233062577,
          "vol20": 0.18998534095,
          "last_vol": 0.026074684,
          "bar_count": 180
        },
        "1D": {
          "status": "ok",
          "last_close": 64268.288,
          "last_time": "2026-07-20T00:00:00Z",
          "ema8": 64190.52873709305,
          "ema20": 63659.00061529218,
          "ema55": 65294.39211408179,
          "rsi14": 52.640516308323164,
          "atr14": 1792.0213874162407,
          "adx14": 23.078195612952243,
          "vol20": 1.4381782021,
          "last_vol": 0.326965217,
          "bar_count": 200
        }
      }
    },
    {
      "symbol": "ETH",
      "pair": "ETH/USD",
      "status": "ok",
      "timeframes": {
        "1H": {
          "status": "ok",
          "last_close": 1869.081,
          "last_time": "2026-07-20T11:00:00Z",
          "ema8": 1864.4699458968828,
          "ema20": 1864.7549525699087,
          "ema55": 1861.9964702737261,
          "rsi14": 53.70455706407416,
          "atr14": 11.486925938390106,
          "adx14": 21.629603121448685,
          "vol20": 0.21452207794999997,
          "last_vol": 0,
          "bar_count": 240
        },
        "4H": {
          "status": "ok",
          "last_close": 1869.081,
          "last_time": "2026-07-20T08:00:00Z",
          "ema8": 1866.7454763691808,
          "ema20": 1861.8735625819832,
          "ema55": 1839.8496874543703,
          "rsi14": 54.69103768161723,
          "atr14": 20.723547468411017,
          "adx14": 13.325130341116903,
          "vol20": 2.6540213089,
          "last_vol": 0.651631018,
          "bar_count": 180
        },
        "1D": {
          "status": "ok",
          "last_close": 1869.081,
          "last_time": "2026-07-20T00:00:00Z",
          "ema8": 1852.2613320826151,
          "ema20": 1806.3389760124464,
          "ema55": 1827.061111799962,
          "rsi14": 59.26132446244435,
          "atr14": 67.61341932869664,
          "adx14": 21.941355549486,
          "vol20": 23.2445819814,
          "last_vol": 2.794704577,
          "bar_count": 200
        }
      }
    },
    {
      "symbol": "SOL",
      "pair": "SOL/USD",
      "status": "ok",
      "timeframes": {
        "1H": {
          "status": "ok",
          "last_close": 76.28,
          "last_time": "2026-07-20T11:00:00Z",
          "ema8": 76.22252181129208,
          "ema20": 76.15508051390697,
          "ema55": 75.90636589707944,
          "rsi14": 52.88208952680719,
          "atr14": 0.578583104536486,
          "adx14": 20.88779726066658,
          "vol20": 3.6443165653999996,
          "last_vol": 0.715706064,
          "bar_count": 240
        },
        "4H": {
          "status": "ok",
          "last_close": 76.28,
          "last_time": "2026-07-20T08:00:00Z",
          "ema8": 76.12659606434704,
          "ema20": 75.92235382568623,
          "ema55": 76.33857210403583,
          "rsi14": 53.83714053682718,
          "atr14": 0.970769716359863,
          "adx14": 16.38439299681249,
          "vol20": 21.07168194285,
          "last_vol": 16.158893064,
          "bar_count": 180
        },
        "1D": {
          "status": "ok",
          "last_close": 76.28,
          "last_time": "2026-07-20T00:00:00Z",
          "ema8": 76.26631049627066,
          "ema20": 76.35539144987277,
          "ema55": 76.79510014054999,
          "rsi14": 50.31101796483492,
          "atr14": 3.060689665499244,
          "adx14": 12.945436162815358,
          "vol20": 205.12313519704998,
          "last_vol": 54.958614981,
          "bar_count": 200
        }
      }
    },
    {
      "symbol": "XRP",
      "pair": "XRP/USD",
      "status": "ok",
      "timeframes": {
        "1H": {
          "status": "ok",
          "last_close": 1.093235,
          "last_time": "2026-07-20T11:00:00Z",
          "ema8": 1.0914614889797956,
          "ema20": 1.0926034450991269,
          "ema55": 1.0929556801869407,
          "rsi14": 50.593899140193216,
          "atr14": 0.006872462313476472,
          "adx14": 16.336809997936488,
          "vol20": 234.64300246855,
          "last_vol": 0,
          "bar_count": 240
        },
        "4H": {
          "status": "ok",
          "last_close": 1.093235,
          "last_time": "2026-07-20T08:00:00Z",
          "ema8": 1.093844492712137,
          "ema20": 1.0936894190495439,
          "ema55": 1.0953864482377011,
          "rsi14": 49.37981911252968,
          "atr14": 0.012054055500823444,
          "adx14": 9.92269093456341,
          "vol20": 1034.4580461382,
          "last_vol": 138.896042,
          "bar_count": 180
        },
        "1D": {
          "status": "ok",
          "last_close": 1.093235,
          "last_time": "2026-07-20T00:00:00Z",
          "ema8": 1.0945895628916316,
          "ema20": 1.0999142339198145,
          "ema55": 1.1542788686642718,
          "rsi14": 46.47118422934929,
          "atr14": 0.03766777338015846,
          "adx14": 13.201929375053279,
          "vol20": 9509.8273655324,
          "last_vol": 2548.525583197,
          "bar_count": 200
        }
      }
    },
    {
      "symbol": "DOGE",
      "pair": "DOGE/USD",
      "status": "ok",
      "timeframes": {
        "1H": {
          "status": "ok",
          "last_close": 0.0721745,
          "last_time": "2026-07-20T11:00:00Z",
          "ema8": 0.0720093985131673,
          "ema20": 0.07211270438523586,
          "ema55": 0.07228493569090208,
          "rsi14": 50.30775974414302,
          "atr14": 0.000416020622407462,
          "adx14": 19.16069061771289,
          "vol20": 87.53259649455,
          "last_vol": 0,
          "bar_count": 240
        },
        "4H": {
          "status": "ok",
          "last_close": 0.0721745,
          "last_time": "2026-07-20T08:00:00Z",
          "ema8": 0.07226430403271744,
          "ema20": 0.07243071375097049,
          "ema55": 0.07294259042377957,
          "rsi14": 45.27615326265758,
          "atr14": 0.0007884042272767137,
          "adx14": 14.361007093413422,
          "vol20": 2977.635519611,
          "last_vol": 0,
          "bar_count": 180
        },
        "1D": {
          "status": "ok",
          "last_close": 0.0721745,
          "last_time": "2026-07-20T00:00:00Z",
          "ema8": 0.07273806969179299,
          "ema20": 0.07418538096052225,
          "ema55": 0.08095875542626739,
          "rsi14": 37.306155247577635,
          "atr14": 0.0027309730556612302,
          "adx14": 32.567396831012324,
          "vol20": 57137.41138759025,
          "last_vol": 1550.18831136,
          "bar_count": 200
        }
      }
    },
    {
      "symbol": "AVAX",
      "pair": "AVAX/USD",
      "status": "ok",
      "timeframes": {
        "1H": {
          "status": "ok",
          "last_close": 6.53779,
          "last_time": "2026-07-20T11:00:00Z",
          "ema8": 6.527206152926649,
          "ema20": 6.514382118976808,
          "ema55": 6.524443531972174,
          "rsi14": 52.75003661828211,
          "atr14": 0.054622974529558735,
          "adx14": 17.210111420878142,
          "vol20": 26.324619276200004,
          "last_vol": 0,
          "bar_count": 240
        },
        "4H": {
          "status": "ok",
          "last_close": 6.53779,
          "last_time": "2026-07-20T08:00:00Z",
          "ema8": 6.527698324230093,
          "ema20": 6.540583345476984,
          "ema55": 6.573362099389005,
          "rsi14": 49.03823853228524,
          "atr14": 0.10104720628002643,
          "adx14": 11.892399586060204,
          "vol20": 137.6507975705,
          "last_vol": 14.333333,
          "bar_count": 180
        },
        "1D": {
          "status": "ok",
          "last_close": 6.53779,
          "last_time": "2026-07-20T00:00:00Z",
          "ema8": 6.558416887131587,
          "ema20": 6.611339929576804,
          "ema55": 7.081237465463983,
          "rsi14": 46.069385158667885,
          "atr14": 0.3255363328890189,
          "adx14": 16.15213806626009,
          "vol20": 1210.4992424112002,
          "last_vol": 415.977335566,
          "bar_count": 200
        }
      }
    },
    {
      "symbol": "LINK",
      "pair": "LINK/USD",
      "status": "ok",
      "timeframes": {
        "1H": {
          "status": "ok",
          "last_close": 8.38586,
          "last_time": "2026-07-20T11:00:00Z",
          "ema8": 8.374587240162532,
          "ema20": 8.36854833419087,
          "ema55": 8.34337488545085,
          "rsi14": 53.176524938827384,
          "atr14": 0.05757775197561787,
          "adx14": 22.03374696109882,
          "vol20": 3.7703890921000003,
          "last_vol": 0,
          "bar_count": 240
        },
        "4H": {
          "status": "ok",
          "last_close": 8.38586,
          "last_time": "2026-07-20T08:00:00Z",
          "ema8": 8.367369495400569,
          "ema20": 8.334888553388861,
          "ema55": 8.218970286940026,
          "rsi14": 56.455995672851216,
          "atr14": 0.1038258114216034,
          "adx14": 14.063951668269178,
          "vol20": 67.25060016455,
          "last_vol": 0,
          "bar_count": 180
        },
        "1D": {
          "status": "ok",
          "last_close": 8.38586,
          "last_time": "2026-07-20T00:00:00Z",
          "ema8": 8.279270217123784,
          "ema20": 8.095463589413004,
          "ema55": 8.201186104390862,
          "rsi14": 58.97061136508088,
          "atr14": 0.3296642360145069,
          "adx14": 17.001119123359285,
          "vol20": 634.7119481482999,
          "last_vol": 52.658700742,
          "bar_count": 200
        }
      }
    },
    {
      "symbol": "DOT",
      "pair": "DOT/USD",
      "status": "ok",
      "timeframes": {
        "1H": {
          "status": "ok",
          "last_close": 0.807814,
          "last_time": "2026-07-20T11:00:00Z",
          "ema8": 0.8077861683311074,
          "ema20": 0.8126691204251649,
          "ema55": 0.8242127753819745,
          "rsi14": 38.62518944551472,
          "atr14": 0.005932940656728366,
          "adx14": 29.727478928500783,
          "vol20": 92.5503486,
          "last_vol": 0,
          "bar_count": 240
        },
        "4H": {
          "status": "ok",
          "last_close": 0.807814,
          "last_time": "2026-07-20T08:00:00Z",
          "ema8": 0.817802750224027,
          "ema20": 0.8292347657054685,
          "ema55": 0.8406889448366426,
          "rsi14": 29.311117596185085,
          "atr14": 0.012339324861465913,
          "adx14": 20.071635495402166,
          "vol20": 204.543700397,
          "last_vol": 0,
          "bar_count": 180
        },
        "1D": {
          "status": "ok",
          "last_close": 0.807814,
          "last_time": "2026-07-20T00:00:00Z",
          "ema8": 0.8337981748306342,
          "ema20": 0.852031642187822,
          "ema55": 0.944880303708069,
          "rsi14": 35.452511286443865,
          "atr14": 0.04094794643097142,
          "adx14": 17.718342086884867,
          "vol20": 1529.07070083,
          "last_vol": 1599.711438,
          "bar_count": 200
        }
      }
    },
    {
      "symbol": "LTC",
      "pair": "LTC/USD",
      "status": "ok",
      "timeframes": {
        "1H": {
          "status": "ok",
          "last_close": 47.03685,
          "last_time": "2026-07-20T11:00:00Z",
          "ema8": 46.918532509763224,
          "ema20": 46.99696953902814,
          "ema55": 46.6836834814052,
          "rsi14": 51.19626159626843,
          "atr14": 0.421533326695445,
          "adx14": 25.741823516359585,
          "vol20": 0.19067431740000002,
          "last_vol": 0,
          "bar_count": 240
        },
        "4H": {
          "status": "ok",
          "last_close": 47.03685,
          "last_time": "2026-07-20T08:00:00Z",
          "ema8": 46.9766909398472,
          "ema20": 46.43104537017131,
          "ema55": 45.492529896631346,
          "rsi14": 61.72690676961835,
          "atr14": 0.714557873623198,
          "adx14": 42.64215479702567,
          "vol20": 1.7186262083500001,
          "last_vol": 0,
          "bar_count": 180
        },
        "1D": {
          "status": "ok",
          "last_close": 47.03685,
          "last_time": "2026-07-20T00:00:00Z",
          "ema8": 45.9398679061474,
          "ema20": 45.0590149243199,
          "ema55": 46.115916280535494,
          "rsi14": 62.62566673794489,
          "atr14": 1.878033230794062,
          "adx14": 25.427836160442293,
          "vol20": 62.38691009065,
          "last_vol": 3.57950954,
          "bar_count": 200
        }
      }
    },
    {
      "symbol": "UNI",
      "pair": "UNI/USD",
      "status": "ok",
      "timeframes": {
        "1H": {
          "status": "ok",
          "last_close": 3.44515,
          "last_time": "2026-07-20T11:00:00Z",
          "ema8": 3.448542239912705,
          "ema20": 3.468782101330991,
          "ema55": 3.503602406102303,
          "rsi14": 39.78226604347717,
          "atr14": 0.027553829937251306,
          "adx14": 18.994226522756826,
          "vol20": 25.577531295,
          "last_vol": 0,
          "bar_count": 240
        },
        "4H": {
          "status": "ok",
          "last_close": 3.44515,
          "last_time": "2026-07-20T08:00:00Z",
          "ema8": 3.4865941714960513,
          "ema20": 3.520548965015995,
          "ema55": 3.5178059730364626,
          "rsi14": 38.95812412941085,
          "atr14": 0.06615932318871935,
          "adx14": 14.004952689304131,
          "vol20": 161.8466989145,
          "last_vol": 44.470603,
          "bar_count": 180
        },
        "1D": {
          "status": "ok",
          "last_close": 3.44515,
          "last_time": "2026-07-20T00:00:00Z",
          "ema8": 3.5224389180362063,
          "ema20": 3.4028985981144846,
          "ema55": 3.238721827355674,
          "rsi14": 55.35664759626528,
          "atr14": 0.22619866474864916,
          "adx14": 41.945520437576896,
          "vol20": 4375.95847798005,
          "last_vol": 497.016800581,
          "bar_count": 200
        }
      }
    }
  ]
}